rerun_animation/__init__.py
rerun_animation/bvh.py
rerun_animation/kinematics.py
rerun_animation/rerun-loader-animation.py
rerun_animation/smpl.py
rerun_animation/util.py
rerun_animation/actions/__init__.py
rerun_animation/actions/app.py
rerun_animation/actions/config.py
rerun_animation/actions/deploy.py
rerun_animation/actions/stream.py
rerun_animation/configs/100style.ini
rerun_animation/configs/amass.ini
rerun_animation/configs/default.ini
rerun_animation/configs/lafan1.ini
rerun_animation/configs/motorica_dance.ini
rerun_animation/configs/trinity_speech_gesture.ini
rerun_animation/configs/zeggs.ini
rerun_animation-0.1.4.dist-info/LICENSE
rerun_animation-0.1.4.dist-info/METADATA
rerun_animation-0.1.4.dist-info/WHEEL
rerun_animation-0.1.4.dist-info/entry_points.txt
rerun_animation-0.1.4.dist-info/top_level.txt
rerun_animation-0.1.4.dist-info/RECORD
