Metadata-Version: 2.1
Name: rerun-animation
Version: 0.1.4
Summary: A rerun-sdk plugin and tools for 3D animation.
Home-page: https://moverseai.github.io/rerun-animation/
Author: Moverse P.C.
Author-email: info@moverse.ai
Project-URL: Documentation, https://moverseai.github.io/rerun-animation/
Project-URL: Source, https://github.com/moverseai/rerun-animation/
Keywords: rerun-sdk,animation,plugin,visualization,3d-animation,3d-visualization,bvh,smpl,smplh,biovision-hierarchy
Classifier: Development Status :: 4 - Beta
Classifier: Intended Audience :: Developers
Classifier: Intended Audience :: Science/Research
Classifier: Programming Language :: Python :: 3.10
Classifier: License :: OSI Approved :: Apache Software License
Classifier: Operating System :: Microsoft :: Windows
Classifier: Operating System :: POSIX :: Linux
Classifier: Topic :: Scientific/Engineering :: Visualization
Classifier: Topic :: Software Development :: Libraries
Classifier: Topic :: Software Development :: Libraries :: Python Modules
Requires-Python: ~=3.10
License-File: LICENSE
Requires-Dist: trimesh >=4.0.5
Requires-Dist: numpy
Requires-Dist: rich >=10.16.1
Requires-Dist: colour ==0.1.5
Requires-Dist: rerun-sdk >=0.18.0
Requires-Dist: importlib-metadata >=7.1.0
